pygql/__init__.py
pygql/client.py
py_gql_next-0.0.2.dist-info/LICENSE
py_gql_next-0.0.2.dist-info/METADATA
py_gql_next-0.0.2.dist-info/WHEEL
py_gql_next-0.0.2.dist-info/top_level.txt
py_gql_next-0.0.2.dist-info/RECORD
