Metadata-Version: 2.1
Name: py-gql-next
Version: 0.0.2
Summary: A simple python GraphQL client
Home-page: https://github.com/wilkice/python-graphql
Author: yan darcy
Author-email: wojiabin@live.cn
License: UNKNOWN
Platform: UNKNOWN
Classifier: Programming Language :: Python :: 3
Classifier: License :: OSI Approved :: MIT License
Classifier: Operating System :: OS Independent
Requires-Python: >=3.6
Requires-Dist: requests
